d6a/__init__.py
ddcmaker/__init__.py
ddcmaker/AI/__init__.py
ddcmaker/AI/cv_ImgAddText.py
ddcmaker/AI/lab_conf.py
ddcmaker/AI/pid.py
ddcmaker/AI/car/__init__.py
ddcmaker/AI/human/__init__.py
ddcmaker/AI/human_code/__init__.py
ddcmaker/AI/human_code/cv_color_stream.py
ddcmaker/AI/human_code/cv_find_hand.py
ddcmaker/AI/human_code/cv_find_stream.py
ddcmaker/AI/human_code/cv_line_patrol.py
ddcmaker/AI/human_code/cv_track_stream.py
ddcmaker/AI/spider/__init__.py
ddcmaker/basic/__init__.py
ddcmaker/basic/hwax.so
ddcmaker/basic/abc/__init__.py
ddcmaker/basic/abc/basic_maker.py
ddcmaker/basic/constant/__init__.py
ddcmaker/basic/constant/lobot_servo_constant.py
ddcmaker/basic/device/__init__.py
ddcmaker/basic/device/serial.py
ddcmaker/basic/device/servo.py
ddcmaker/basic/device/pwm/__init__.py
ddcmaker/basic/device/pwm/car.py
ddcmaker/basic/device/pwm/robot.py
ddcmaker/basic/system/__init__.py
ddcmaker/basic/system/host.py
ddcmaker/basic/system/process.py
ddcmaker/decorator/__init__.py
ddcmaker/decorator/safety.py
ddcmaker/maker/__init__.py
ddcmaker/maker/car/__init__.py
ddcmaker/maker/car/car.py
ddcmaker/maker/car/actions/__init__.py
ddcmaker/maker/car/actions/ai.py
ddcmaker/maker/car/actions/normal.py
ddcmaker/maker/human/AI_human.py
ddcmaker/maker/human/__init__.py
ddcmaker/maker/human/ad_mode.py
ddcmaker/maker/human/robot.py
ddcmaker/maker/human_code/__init__.py
ddcmaker/maker/human_code/controller.py
ddcmaker/maker/human_code/robot.py
ddcmaker/maker/human_code/actions/__init__.py
ddcmaker/maker/human_code/actions/ai.py
ddcmaker/maker/human_code/actions/dance.py
ddcmaker/maker/human_code/actions/gymnastic.py
ddcmaker/maker/human_code/actions/head.py
ddcmaker/maker/human_code/actions/normal.py
ddcmaker/maker/human_code/actions/wushu.py
ddcmaker/maker/spider/__init__.py
ddcmaker/maker/spider/spider.py
ddcmaker/maker/spider/actions/__init__.py
ddcmaker/maker/spider/actions/ai.py
ddcmaker/maker/spider/actions/normal.py
ddcmaker/public/LeServo.py
ddcmaker/public/PWMServo.py
ddcmaker-0.0.29.dist-info/LICENSE.txt
ddcmaker-0.0.29.dist-info/METADATA
ddcmaker-0.0.29.dist-info/WHEEL
ddcmaker-0.0.29.dist-info/top_level.txt
ddcmaker-0.0.29.dist-info/RECORD
