Metadata-Version: 2.1
Name: ddcmaker
Version: 0.0.29
Summary: This is a package for Raspberry pie system of maker  
Home-page: https://github.com/NocoldBob/robot
Author: fastbiubiu
Author-email: fastbiubiu@163.com
License: UNKNOWN
Platform: Linux
Classifier: Topic :: System :: Operating System Kernels :: Linux
Classifier: Programming Language :: Python :: 3.5
Classifier: Programming Language :: Python :: 3.6
Classifier: Programming Language :: Python :: 3.7
Classifier: Programming Language :: Python :: 3.8
Classifier: License :: OSI Approved :: MIT License
Classifier: Operating System :: POSIX :: Linux
Requires-Python: >=3
Requires-Dist: bottle
Requires-Dist: marshmallow
Requires-Dist: AIserver
Requires-Dist: flask
Requires-Dist: pyserial
